StudyCode/mod_2_n/mod_2_n.v
module mod_2_n(
    input clk,
    input rst_n,
    output MyFlag
);

reg [5:0] data_cnt;
reg [5:0] rd_addr;
reg [5:0] wr_addr;

always @(posedge clk or negedge rst_n) begin
    if (~rst_n) begin
        data_cnt <= 6'd0;
    end else begin
        data_cnt <= data_cnt + 1;
    end
end

always @(posedge clk or negedge rst_n) begin
    if (~rst_n) begin
        rd_addr <=  6'd0;
        wr_addr <=  6'd0;
    end else begin
        rd_addr = (48 + data_cnt) % 64;
        wr_addr = (48 + data_cnt) & 6'h3F; // 与63(111111)进行位与操作
    end
end

assign MyFlag = wr_addr == rd_addr;

endmodule

StudyCode/mod_2_n/tb_mod_2_n.v
`timescale 1ns/1ps

module tb_mod_2_n();
    // 定义测试信号
    reg clk;
    reg rst_n;
    wire MyFlag;
    
    // 实例化被测模块
    mod_2_n dut (
        .clk(clk),
        .rst_n(rst_n),
        .MyFlag(MyFlag)
    );
    
    // 时钟生成
    initial begin
        clk = 0;
        forever #5 clk = ~clk; // 10ns周期（100MHz）时钟
    end
    
    // 测试过程
    initial begin
        // 波形输出
        $dumpfile("tb_mod_2_n.vcd");
        $dumpvars(0, tb_mod_2_n);
        
        // 初始复位
        rst_n = 0;
        #20;
        rst_n = 1;
        
        // 运行足够长的时间以观察多个周期
        #1500; // 运行150个时钟周期，足以观察64个计数和环绕
        
        // 再次复位测试
        rst_n = 0;
        #20;
        rst_n = 1;
        #680;
        
        $display("测试完成");
        $finish;
    end
    
    // 监控信号
    initial begin
        $monitor("Time=%0t, rst_n=%b, wr_addr=%d, rd_addr=%d, MyFlag=%b", 
                 $time, rst_n, dut.wr_addr, dut.rd_addr, MyFlag);
    end
    
endmodule

StudyCode/mod_2_n/tb_mod_2_n.vcd
$date
	Mon Mar 17 20:31:50 2025
$end
$version
	Icarus Verilog
$end
$timescale
	1ps
$end
$scope module tb_mod_2_n $end
$var wire 1 ! MyFlag $end
$var reg 1 " clk $end
$var reg 1 # rst_n $end
$scope module dut $end
$var wire 1 " clk $end
$var wire 1 # rst_n $end
$var wire 1 ! MyFlag $end
$var reg 6 $ data_cnt [5:0] $end
$var reg 6 % rd_addr [5:0] $end
$var reg 6 & wr_addr [5:0] $end
$upscope $end
$upscope $end
$enddefinitions $end
$comment Show the parameter values. $end
$dumpall
$end
#0
$dumpvars
b0 &
b0 %
b0 $
0#
0"
1!
$end
#5000
1"
#10000
0"
#15000
1"
#20000
0"
1#
#25000
b1 $
b110000 &
1!
b110000 %
1"
#30000
0"
#35000
b10 $
b110001 &
1!
b110001 %
1"
#40000
0"
#45000
b11 $
b110010 &
1!
b110010 %
1"
#50000
0"
#55000
b100 $
b110011 &
1!
b110011 %
1"
#60000
0"
#65000
b101 $
b110100 &
1!
b110100 %
1"
#70000
0"
#75000
b110 $
b110101 &
1!
b110101 %
1"
#80000
0"
#85000
b111 $
b110110 &
1!
b110110 %
1"
#90000
0"
#95000
b1000 $
b110111 &
1!
b110111 %
1"
#100000
0"
#105000
b1001 $
b111000 &
1!
b111000 %
1"
#110000
0"
#115000
b1010 $
b111001 &
1!
b111001 %
1"
#120000
0"
#125000
b1011 $
b111010 &
1!
b111010 %
1"
#130000
0"
#135000
b1100 $
b111011 &
1!
b111011 %
1"
#140000
0"
#145000
b1101 $
b111100 &
1!
b111100 %
1"
#150000
0"
#155000
b1110 $
b111101 &
1!
b111101 %
1"
#160000
0"
#165000
b1111 $
b111110 &
1!
b111110 %
1"
#170000
0"
#175000
b10000 $
b111111 &
1!
b111111 %
1"
#180000
0"
#185000
b10001 $
b0 &
1!
b0 %
1"
#190000
0"
#195000
b10010 $
b1 &
1!
b1 %
1"
#200000
0"
#205000
b10011 $
b10 &
1!
b10 %
1"
#210000
0"
#215000
b10100 $
b11 &
1!
b11 %
1"
#220000
0"
#225000
b10101 $
b100 &
1!
b100 %
1"
#230000
0"
#235000
b10110 $
b101 &
1!
b101 %
1"
#240000
0"
#245000
b10111 $
b110 &
1!
b110 %
1"
#250000
0"
#255000
b11000 $
b111 &
1!
b111 %
1"
#260000
0"
#265000
b11001 $
b1000 &
1!
b1000 %
1"
#270000
0"
#275000
b11010 $
b1001 &
1!
b1001 %
1"
#280000
0"
#285000
b11011 $
b1010 &
1!
b1010 %
1"
#290000
0"
#295000
b11100 $
b1011 &
1!
b1011 %
1"
#300000
0"
#305000
b11101 $
b1100 &
1!
b1100 %
1"
#310000
0"
#315000
b11110 $
b1101 &
1!
b1101 %
1"
#320000
0"
#325000
b11111 $
b1110 &
1!
b1110 %
1"
#330000
0"
#335000
b100000 $
b1111 &
1!
b1111 %
1"
#340000
0"
#345000
b100001 $
b10000 &
1!
b10000 %
1"
#350000
0"
#355000
b100010 $
b10001 &
1!
b10001 %
1"
#360000
0"
#365000
b100011 $
b10010 &
1!
b10010 %
1"
#370000
0"
#375000
b100100 $
b10011 &
1!
b10011 %
1"
#380000
0"
#385000
b100101 $
b10100 &
1!
b10100 %
1"
#390000
0"
#395000
b100110 $
b10101 &
1!
b10101 %
1"
#400000
0"
#405000
b100111 $
b10110 &
1!
b10110 %
1"
#410000
0"
#415000
b101000 $
b10111 &
1!
b10111 %
1"
#420000
0"
#425000
b101001 $
b11000 &
1!
b11000 %
1"
#430000
0"
#435000
b101010 $
b11001 &
1!
b11001 %
1"
#440000
0"
#445000
b101011 $
b11010 &
1!
b11010 %
1"
#450000
0"
#455000
b101100 $
b11011 &
1!
b11011 %
1"
#460000
0"
#465000
b101101 $
b11100 &
1!
b11100 %
1"
#470000
0"
#475000
b101110 $
b11101 &
1!
b11101 %
1"
#480000
0"
#485000
b101111 $
b11110 &
1!
b11110 %
1"
#490000
0"
#495000
b110000 $
b11111 &
1!
b11111 %
1"
#500000
0"
#505000
b110001 $
b100000 &
1!
b100000 %
1"
#510000
0"
#515000
b110010 $
b100001 &
1!
b100001 %
1"
#520000
0"
#525000
b110011 $
b100010 &
1!
b100010 %
1"
#530000
0"
#535000
b110100 $
b100011 &
1!
b100011 %
1"
#540000
0"
#545000
b110101 $
b100100 &
1!
b100100 %
1"
#550000
0"
#555000
b110110 $
b100101 &
1!
b100101 %
1"
#560000
0"
#565000
b110111 $
b100110 &
1!
b100110 %
1"
#570000
0"
#575000
b111000 $
b100111 &
1!
b100111 %
1"
#580000
0"
#585000
b111001 $
b101000 &
1!
b101000 %
1"
#590000
0"
#595000
b111010 $
b101001 &
1!
b101001 %
1"
#600000
0"
#605000
b111011 $
b101010 &
1!
b101010 %
1"
#610000
0"
#615000
b111100 $
b101011 &
1!
b101011 %
1"
#620000
0"
#625000
b111101 $
b101100 &
1!
b101100 %
1"
#630000
0"
#635000
b111110 $
b101101 &
1!
b101101 %
1"
#640000
0"
#645000
b111111 $
b101110 &
1!
b101110 %
1"
#650000
0"
#655000
b0 $
b101111 &
1!
b101111 %
1"
#660000
0"
#665000
b1 $
b110000 &
1!
b110000 %
1"
#670000
0"
#675000
b10 $
b110001 &
1!
b110001 %
1"
#680000
0"
#685000
b11 $
b110010 &
1!
b110010 %
1"
#690000
0"
#695000
b100 $
b110011 &
1!
b110011 %
1"
#700000
0"
#705000
b101 $
b110100 &
1!
b110100 %
1"
#710000
0"
#715000
b110 $
b110101 &
1!
b110101 %
1"
#720000
0"
#725000
b111 $
b110110 &
1!
b110110 %
1"
#730000
0"
#735000
b1000 $
b110111 &
1!
b110111 %
1"
#740000
0"
#745000
b1001 $
b111000 &
1!
b111000 %
1"
#750000
0"
#755000
b1010 $
b111001 &
1!
b111001 %
1"
#760000
0"
#765000
b1011 $
b111010 &
1!
b111010 %
1"
#770000
0"
#775000
b1100 $
b111011 &
1!
b111011 %
1"
#780000
0"
#785000
b1101 $
b111100 &
1!
b111100 %
1"
#790000
0"
#795000
b1110 $
b111101 &
1!
b111101 %
1"
#800000
0"
#805000
b1111 $
b111110 &
1!
b111110 %
1"
#810000
0"
#815000
b10000 $
b111111 &
1!
b111111 %
1"
#820000
0"
#825000
b10001 $
b0 &
1!
b0 %
1"
#830000
0"
#835000
b10010 $
b1 &
1!
b1 %
1"
#840000
0"
#845000
b10011 $
b10 &
1!
b10 %
1"
#850000
0"
#855000
b10100 $
b11 &
1!
b11 %
1"
#860000
0"
#865000
b10101 $
b100 &
1!
b100 %
1"
#870000
0"
#875000
b10110 $
b101 &
1!
b101 %
1"
#880000
0"
#885000
b10111 $
b110 &
1!
b110 %
1"
#890000
0"
#895000
b11000 $
b111 &
1!
b111 %
1"
#900000
0"
#905000
b11001 $
b1000 &
1!
b1000 %
1"
#910000
0"
#915000
b11010 $
b1001 &
1!
b1001 %
1"
#920000
0"
#925000
b11011 $
b1010 &
1!
b1010 %
1"
#930000
0"
#935000
b11100 $
b1011 &
1!
b1011 %
1"
#940000
0"
#945000
b11101 $
b1100 &
1!
b1100 %
1"
#950000
0"
#955000
b11110 $
b1101 &
1!
b1101 %
1"
#960000
0"
#965000
b11111 $
b1110 &
1!
b1110 %
1"
#970000
0"
#975000
b100000 $
b1111 &
1!
b1111 %
1"
#980000
0"
#985000
b100001 $
b10000 &
1!
b10000 %
1"
#990000
0"
#995000
b100010 $
b10001 &
1!
b10001 %
1"
#1000000
0"
#1005000
b100011 $
b10010 &
1!
b10010 %
1"
#1010000
0"
#1015000
b100100 $
b10011 &
1!
b10011 %
1"
#1020000
0"
#1025000
b100101 $
b10100 &
1!
b10100 %
1"
#1030000
0"
#1035000
b100110 $
b10101 &
1!
b10101 %
1"
#1040000
0"
#1045000
b100111 $
b10110 &
1!
b10110 %
1"
#1050000
0"
#1055000
b101000 $
b10111 &
1!
b10111 %
1"
#1060000
0"
#1065000
b101001 $
b11000 &
1!
b11000 %
1"
#1070000
0"
#1075000
b101010 $
b11001 &
1!
b11001 %
1"
#1080000
0"
#1085000
b101011 $
b11010 &
1!
b11010 %
1"
#1090000
0"
#1095000
b101100 $
b11011 &
1!
b11011 %
1"
#1100000
0"
#1105000
b101101 $
b11100 &
1!
b11100 %
1"
#1110000
0"
#1115000
b101110 $
b11101 &
1!
b11101 %
1"
#1120000
0"
#1125000
b101111 $
b11110 &
1!
b11110 %
1"
#1130000
0"
#1135000
b110000 $
b11111 &
1!
b11111 %
1"
#1140000
0"
#1145000
b110001 $
b100000 &
1!
b100000 %
1"
#1150000
0"
#1155000
b110010 $
b100001 &
1!
b100001 %
1"
#1160000
0"
#1165000
b110011 $
b100010 &
1!
b100010 %
1"
#1170000
0"
#1175000
b110100 $
b100011 &
1!
b100011 %
1"
#1180000
0"
#1185000
b110101 $
b100100 &
1!
b100100 %
1"
#1190000
0"
#1195000
b110110 $
b100101 &
1!
b100101 %
1"
#1200000
0"
#1205000
b110111 $
b100110 &
1!
b100110 %
1"
#1210000
0"
#1215000
b111000 $
b100111 &
1!
b100111 %
1"
#1220000
0"
#1225000
b111001 $
b101000 &
1!
b101000 %
1"
#1230000
0"
#1235000
b111010 $
b101001 &
1!
b101001 %
1"
#1240000
0"
#1245000
b111011 $
b101010 &
1!
b101010 %
1"
#1250000
0"
#1255000
b111100 $
b101011 &
1!
b101011 %
1"
#1260000
0"
#1265000
b111101 $
b101100 &
1!
b101100 %
1"
#1270000
0"
#1275000
b111110 $
b101101 &
1!
b101101 %
1"
#1280000
0"
#1285000
b111111 $
b101110 &
1!
b101110 %
1"
#1290000
0"
#1295000
b0 $
b101111 &
1!
b101111 %
1"
#1300000
0"
#1305000
b1 $
b110000 &
1!
b110000 %
1"
#1310000
0"
#1315000
b10 $
b110001 &
1!
b110001 %
1"
#1320000
0"
#1325000
b11 $
b110010 &
1!
b110010 %
1"
#1330000
0"
#1335000
b100 $
b110011 &
1!
b110011 %
1"
#1340000
0"
#1345000
b101 $
b110100 &
1!
b110100 %
1"
#1350000
0"
#1355000
b110 $
b110101 &
1!
b110101 %
1"
#1360000
0"
#1365000
b111 $
b110110 &
1!
b110110 %
1"
#1370000
0"
#1375000
b1000 $
b110111 &
1!
b110111 %
1"
#1380000
0"
#1385000
b1001 $
b111000 &
1!
b111000 %
1"
#1390000
0"
#1395000
b1010 $
b111001 &
1!
b111001 %
1"
#1400000
0"
#1405000
b1011 $
b111010 &
1!
b111010 %
1"
#1410000
0"
#1415000
b1100 $
b111011 &
1!
b111011 %
1"
#1420000
0"
#1425000
b1101 $
b111100 &
1!
b111100 %
1"
#1430000
0"
#1435000
b1110 $
b111101 &
1!
b111101 %
1"
#1440000
0"
#1445000
b1111 $
b111110 &
1!
b111110 %
1"
#1450000
0"
#1455000
b10000 $
b111111 &
1!
b111111 %
1"
#1460000
0"
#1465000
b10001 $
b0 &
1!
b0 %
1"
#1470000
0"
#1475000
b10010 $
b1 &
1!
b1 %
1"
#1480000
0"
#1485000
b10011 $
b10 &
1!
b10 %
1"
#1490000
0"
#1495000
b10100 $
b11 &
1!
b11 %
1"
#1500000
0"
#1505000
b10101 $
b100 &
1!
b100 %
1"
#1510000
0"
#1515000
b10110 $
b101 &
1!
b101 %
1"
#1520000
b0 &
1!
b0 %
b0 $
0"
0#
#1525000
1"
#1530000
0"
#1535000
1"
#1540000
0"
1#
#1545000
b1 $
b110000 &
1!
b110000 %
1"
#1550000
0"
#1555000
b10 $
b110001 &
1!
b110001 %
1"
#1560000
0"
#1565000
b11 $
b110010 &
1!
b110010 %
1"
#1570000
0"
#1575000
b100 $
b110011 &
1!
b110011 %
1"
#1580000
0"
#1585000
b101 $
b110100 &
1!
b110100 %
1"
#1590000
0"
#1595000
b110 $
b110101 &
1!
b110101 %
1"
#1600000
0"
#1605000
b111 $
b110110 &
1!
b110110 %
1"
#1610000
0"
#1615000
b1000 $
b110111 &
1!
b110111 %
1"
#1620000
0"
#1625000
b1001 $
b111000 &
1!
b111000 %
1"
#1630000
0"
#1635000
b1010 $
b111001 &
1!
b111001 %
1"
#1640000
0"
#1645000
b1011 $
b111010 &
1!
b111010 %
1"
#1650000
0"
#1655000
b1100 $
b111011 &
1!
b111011 %
1"
#1660000
0"
#1665000
b1101 $
b111100 &
1!
b111100 %
1"
#1670000
0"
#1675000
b1110 $
b111101 &
1!
b111101 %
1"
#1680000
0"
#1685000
b1111 $
b111110 &
1!
b111110 %
1"
#1690000
0"
#1695000
b10000 $
b111111 &
1!
b111111 %
1"
#1700000
0"
#1705000
b10001 $
b0 &
1!
b0 %
1"
#1710000
0"
#1715000
b10010 $
b1 &
1!
b1 %
1"
#1720000
0"
#1725000
b10011 $
b10 &
1!
b10 %
1"
#1730000
0"
#1735000
b10100 $
b11 &
1!
b11 %
1"
#1740000
0"
#1745000
b10101 $
b100 &
1!
b100 %
1"
#1750000
0"
#1755000
b10110 $
b101 &
1!
b101 %
1"
#1760000
0"
#1765000
b10111 $
b110 &
1!
b110 %
1"
#1770000
0"
#1775000
b11000 $
b111 &
1!
b111 %
1"
#1780000
0"
#1785000
b11001 $
b1000 &
1!
b1000 %
1"
#1790000
0"
#1795000
b11010 $
b1001 &
1!
b1001 %
1"
#1800000
0"
#1805000
b11011 $
b1010 &
1!
b1010 %
1"
#1810000
0"
#1815000
b11100 $
b1011 &
1!
b1011 %
1"
#1820000
0"
#1825000
b11101 $
b1100 &
1!
b1100 %
1"
#1830000
0"
#1835000
b11110 $
b1101 &
1!
b1101 %
1"
#1840000
0"
#1845000
b11111 $
b1110 &
1!
b1110 %
1"
#1850000
0"
#1855000
b100000 $
b1111 &
1!
b1111 %
1"
#1860000
0"
#1865000
b100001 $
b10000 &
1!
b10000 %
1"
#1870000
0"
#1875000
b100010 $
b10001 &
1!
b10001 %
1"
#1880000
0"
#1885000
b100011 $
b10010 &
1!
b10010 %
1"
#1890000
0"
#1895000
b100100 $
b10011 &
1!
b10011 %
1"
#1900000
0"
#1905000
b100101 $
b10100 &
1!
b10100 %
1"
#1910000
0"
#1915000
b100110 $
b10101 &
1!
b10101 %
1"
#1920000
0"
#1925000
b100111 $
b10110 &
1!
b10110 %
1"
#1930000
0"
#1935000
b101000 $
b10111 &
1!
b10111 %
1"
#1940000
0"
#1945000
b101001 $
b11000 &
1!
b11000 %
1"
#1950000
0"
#1955000
b101010 $
b11001 &
1!
b11001 %
1"
#1960000
0"
#1965000
b101011 $
b11010 &
1!
b11010 %
1"
#1970000
0"
#1975000
b101100 $
b11011 &
1!
b11011 %
1"
#1980000
0"
#1985000
b101101 $
b11100 &
1!
b11100 %
1"
#1990000
0"
#1995000
b101110 $
b11101 &
1!
b11101 %
1"
#2000000
0"
#2005000
b101111 $
b11110 &
1!
b11110 %
1"
#2010000
0"
#2015000
b110000 $
b11111 &
1!
b11111 %
1"
#2020000
0"
#2025000
b110001 $
b100000 &
1!
b100000 %
1"
#2030000
0"
#2035000
b110010 $
b100001 &
1!
b100001 %
1"
#2040000
0"
#2045000
b110011 $
b100010 &
1!
b100010 %
1"
#2050000
0"
#2055000
b110100 $
b100011 &
1!
b100011 %
1"
#2060000
0"
#2065000
b110101 $
b100100 &
1!
b100100 %
1"
#2070000
0"
#2075000
b110110 $
b100101 &
1!
b100101 %
1"
#2080000
0"
#2085000
b110111 $
b100110 &
1!
b100110 %
1"
#2090000
0"
#2095000
b111000 $
b100111 &
1!
b100111 %
1"
#2100000
0"
#2105000
b111001 $
b101000 &
1!
b101000 %
1"
#2110000
0"
#2115000
b111010 $
b101001 &
1!
b101001 %
1"
#2120000
0"
#2125000
b111011 $
b101010 &
1!
b101010 %
1"
#2130000
0"
#2135000
b111100 $
b101011 &
1!
b101011 %
1"
#2140000
0"
#2145000
b111101 $
b101100 &
1!
b101100 %
1"
#2150000
0"
#2155000
b111110 $
b101101 &
1!
b101101 %
1"
#2160000
0"
#2165000
b111111 $
b101110 &
1!
b101110 %
1"
#2170000
0"
#2175000
b0 $
b101111 &
1!
b101111 %
1"
#2180000
0"
#2185000
b1 $
b110000 &
1!
b110000 %
1"
#2190000
0"
#2195000
b10 $
b110001 &
1!
b110001 %
1"
#2200000
0"
#2205000
b11 $
b110010 &
1!
b110010 %
1"
#2210000
0"
#2215000
b100 $
b110011 &
1!
b110011 %
1"
